{
  "cities": [
    {
      "cityName": "Marston Montgomery",
      "country": "United Kingdom of Great Britain and Northern Ireland (the)",
      "emoji": "GB",
      "date": "2023-10-13T19:18:35.930Z",
      "notes": "",
      "position": {
        "lat": "52.93539665862318",
        "lng": "-1.77978515625"
      },
      "id": 1
    },
    {
      "cityName": "Delhi",
      "country": "India",
      "emoji": "IN",
      "date": "2023-10-13T20:41:35.938Z",
      "notes": "wow",
      "position": {
        "lat": "28.671310915880834",
        "lng": "77.10205078125001"
      },
      "id": 2
    }
  ]
}